py_eicar/__init__.py
py_eicar-0.1.0.dist-info/WHEEL
py_eicar-0.1.0.dist-info/METADATA
py_eicar-0.1.0.dist-info/RECORD
